sbmlaliasnodecreator/__init__.py
sbmlaliasnodecreator/sbmlaliasnodecreator.py
sbmlaliasnodecreator-0.0.5.data/scripts/example1.py
sbmlaliasnodecreator-0.0.5.data/scripts/example2.py
sbmlaliasnodecreator-0.0.5.dist-info/LICENSE
sbmlaliasnodecreator-0.0.5.dist-info/METADATA
sbmlaliasnodecreator-0.0.5.dist-info/WHEEL
sbmlaliasnodecreator-0.0.5.dist-info/top_level.txt
sbmlaliasnodecreator-0.0.5.dist-info/RECORD
