Metadata-Version: 2.1
Name: sbmlaliasnodecreator
Version: 0.0.5
Summary: Create alias nodes for heavily connected nodes in an SBML model
Home-page: https://github.com/adelhpour/SBMLAliasNodeCreator
Author: Adel Heydarabadipour
Author-email: adelhp@uw.edu
Project-URL: Bug Tracker, https://github.com/adelhpour/SBMLAliasNodeCreator/issues
Classifier: Programming Language :: Python :: 3
Classifier: License :: OSI Approved :: MIT License
Classifier: Operating System :: OS Independent
Requires-Python: >=3.8
License-File: LICENSE
Requires-Dist: libsbml
Requires-Dist: SBMLDiagrams (==1.3.2)
